SEAL/SplineFunction.py
SEAL/SplineSpace.py
SEAL/TensorProductSplineFunction.py
SEAL/TensorProductSplineSpace.py
SEAL/__init__.py
SEAL/approximation.py
SEAL/interpolation.py
SEAL/lib.py
spline_algorithm_library-1.0.0.dist-info/WHEEL
spline_algorithm_library-1.0.0.dist-info/METADATA
spline_algorithm_library-1.0.0.dist-info/RECORD
