Metadata-Version: 2.1
Name: spline-algorithm-library
Version: 1.0.0
Summary: A spline library written in Python
License: MIT
Author: Ivar Stangeby
Requires-Python: >=3.8,<4.0
Classifier: License :: OSI Approved :: MIT License
Classifier: Programming Language :: Python :: 3
Classifier: Programming Language :: Python :: 3.10
Classifier: Programming Language :: Python :: 3.8
Classifier: Programming Language :: Python :: 3.9
Requires-Dist: numpy (>=1.22.2,<2.0.0)
